stripe_models.py
Stripe_Firebase_Py-0.2.dist-info/LICENSE
Stripe_Firebase_Py-0.2.dist-info/METADATA
Stripe_Firebase_Py-0.2.dist-info/WHEEL
Stripe_Firebase_Py-0.2.dist-info/top_level.txt
Stripe_Firebase_Py-0.2.dist-info/RECORD
