Metadata-Version: 2.1
Name: Stripe-Firebase-Py
Version: 0.2
License: MIT
License-File: LICENSE
Requires-Dist: stripe
Requires-Dist: google-cloud-firestore
